src/__init__.py
src/global_var.py
src/ml_socket.py
src/pyfed.py
pyfedm-0.0.1.dist-info/METADATA
pyfedm-0.0.1.dist-info/WHEEL
pyfedm-0.0.1.dist-info/licenses/LICENSE
pyfedm-0.0.1.dist-info/RECORD
