Metadata-Version: 2.1
Name: pyfedm
Version: 0.0.1
Summary: PyFed is an open-source framework for federated learning algorithms.
Project-URL: Homepage, https://github.com/amirrezasokhankhosh/PyFed
Project-URL: Bug Tracker, https://github.com/amirrezasokhankhosh/PyFed/issues
Author-email: Amirreza Sokhankhosh <amirreza.sokhankhosh@gmail.com>
License-File: LICENSE
Classifier: License :: OSI Approved :: MIT License
Classifier: Operating System :: MacOS
Classifier: Programming Language :: Python :: 3
Requires-Python: >=3.7
Requires-Dist: h5py>=3.6.0
Requires-Dist: numpy>=1.23.0
Requires-Dist: tensorboard>=2.10.0
Requires-Dist: tensorflow-macos>=2.10.0
